mtmai/.gitignore
mtmai/__init__.py
mtmai/_version.py
mtmai/agent_runner copy.py
mtmai/agent_runner.py
mtmai/appium_test.py
mtmai/auth.py
mtmai/config.example.toml
mtmai/config.toml
mtmai/daytona_utils.py
mtmai/deps.py
mtmai/hatchet_client.py
mtmai/hello_f2.py
mtmai/main.py
mtmai/mtmai_app.py
mtmai/openapi-generator-config.yaml
mtmai/openapi_mtmai.json
mtmai/otel.py
mtmai/sandbox_utils.py
mtmai/server.py
mtmai/supabase_demo.py
mtmai/worker_main.py
mtmai/用例.md
mtmai/自动发布到小红色.md
mtmai/NarratoAI/_webui.py
mtmai/NarratoAI/config.py
mtmai/NarratoAI/schema.py
mtmai/NarratoAI/video_pipeline.py
mtmai/NarratoAI/resource/fonts/.gitkeep
mtmai/NarratoAI/resource/fonts/MicrosoftYaHeiNormal.ttc
mtmai/NarratoAI/resource/fonts/字体列表.md
mtmai/NarratoAI/services/audio_merger.py
mtmai/NarratoAI/services/llm.py
mtmai/NarratoAI/services/material.py
mtmai/NarratoAI/services/script_service.py
mtmai/NarratoAI/services/state.py
mtmai/NarratoAI/services/subtitle.py
mtmai/NarratoAI/services/task.py
mtmai/NarratoAI/services/video.py
mtmai/NarratoAI/services/video_service.py
mtmai/NarratoAI/services/voice.py
mtmai/NarratoAI/utils/check_script.py
mtmai/NarratoAI/utils/gemini_analyzer.py
mtmai/NarratoAI/utils/mpt_utils.py
mtmai/NarratoAI/utils/qwenvl_analyzer.py
mtmai/NarratoAI/utils/script_generator.py
mtmai/NarratoAI/utils/utils.py
mtmai/NarratoAI/utils/video_processor.py
mtmai/NarratoAI/utils/video_processor_v2.py
mtmai/NarratoAI/webui/__init__.py
mtmai/NarratoAI/webui/components/__init__.py
mtmai/NarratoAI/webui/components/audio_settings.py
mtmai/NarratoAI/webui/components/basic_settings.py
mtmai/NarratoAI/webui/components/merge_settings.py
mtmai/NarratoAI/webui/components/review_settings.py
mtmai/NarratoAI/webui/components/script_settings.py
mtmai/NarratoAI/webui/components/subtitle_settings.py
mtmai/NarratoAI/webui/components/system_settings.py
mtmai/NarratoAI/webui/components/video_settings.py
mtmai/NarratoAI/webui/config/settings.py
mtmai/NarratoAI/webui/i18n/__init__.py
mtmai-0.7.30.dist-info/METADATA
mtmai-0.7.30.dist-info/WHEEL
mtmai-0.7.30.dist-info/entry_points.txt
mtmai-0.7.30.dist-info/RECORD
